{
  "passed_at": "2026-07-02T20:13:37Z",
  "planning_lint": {
    "tool": "/agile-refinement Mode 1",
    "scope": "planning/edger/",
    "red_flags": 0,
    "oracle": "refinement-lint.py"
  },
  "path_preflight": {
    "missing": 0
  },
  "extension_validation": {
    "status": "passed",
    "module": "gateway"
  },
  "bun_test": {
    "status": "skipped",
    "reason": "no root JS/TS test suite"
  },
  "memory_lint": {
    "excluded": true,
    "reason": "server stability \u2014 operator directive 2026-06-29"
  }
}
